README
configure.py
setup.py
configure.egg-info/PKG-INFO
configure.egg-info/SOURCES.txt
configure.egg-info/dependency_links.txt
configure.egg-info/not-zip-safe
configure.egg-info/requires.txt
configure.egg-info/top_level.txt