Metadata-Version: 1.0
Name: configure
Version: 0.4.4
Summary: configuration toolkit based on YAML
Home-page: UNKNOWN
Author: Andrey Popp
Author-email: 8mayday@gmail.com
License: UNKNOWN
Platform: UNKNOWN
